{
  "season": 2026,
  "generatedAt": "Thursday, June 25, 2026 at 3:34 PM EDT",
  "teams": [
    {
      "name": "Los Angeles Angels",
      "abbreviation": "LAA",
      "division": "American League West",
      "league": "American League",
      "w": 34,
      "l": 48,
      "pct": ".415",
      "gb": "7.0",
      "previousGb": "8.5",
      "gbChange": 1.5,
      "wcGb": "6.0",
      "previousWcGb": "7.0",
      "wcGbChange": 1,
      "wcRank": "11",
      "clinchIndicator": null,
      "rs": 374,
      "ra": 410,
      "rd": -36,
      "pythWins": 37.2,
      "pythVar": -3.24,
      "streak": "W2",
      "splits": {
        "last10": "5-5",
        "home": "19-21",
        "away": "15-27",
        "division": null,
        "league": null,
        "winners": "14-26"
      },
      "stats": {
        "obp": 0.319,
        "slg": 0.398,
        "ops": 0.717,
        "fip": 4.43,
        "der": 0.696
      }
    },
    {
      "name": "Arizona Diamondbacks",
      "abbreviation": "AZ",
      "division": "National League West",
      "league": "National League",
      "w": 41,
      "l": 39,
      "pct": ".512",
      "gb": "10.5",
      "previousGb": "10.5",
      "gbChange": 0,
      "wcGb": "2.0",
      "previousWcGb": "1.5",
      "wcGbChange": -0.5,
      "wcRank": "6",
      "clinchIndicator": null,
      "rs": 346,
      "ra": 366,
      "rd": -20,
      "pythWins": 37.8,
      "pythVar": 3.25,
      "streak": "W2",
      "splits": {
        "last10": "6-4",
        "home": "24-17",
        "away": "17-22",
        "division": null,
        "league": null,
        "winners": "13-27"
      },
      "stats": {
        "obp": 0.31,
        "slg": 0.386,
        "ops": 0.696,
        "fip": 4.42,
        "der": 0.71
      }
    },
    {
      "name": "Baltimore Orioles",
      "abbreviation": "BAL",
      "division": "American League East",
      "league": "American League",
      "w": 38,
      "l": 44,
      "pct": ".463",
      "gb": "11.5",
      "previousGb": "10.5",
      "gbChange": -1,
      "wcGb": "2.0",
      "previousWcGb": "2.0",
      "wcGbChange": 0,
      "wcRank": "7",
      "clinchIndicator": null,
      "rs": 382,
      "ra": 407,
      "rd": -25,
      "pythWins": 38.4,
      "pythVar": -0.4,
      "streak": "L2",
      "splits": {
        "last10": "4-6",
        "home": "22-19",
        "away": "16-25",
        "division": null,
        "league": null,
        "winners": "19-26"
      },
      "stats": {
        "obp": 0.32,
        "slg": 0.402,
        "ops": 0.722,
        "fip": 4.27,
        "der": 0.687
      }
    },
    {
      "name": "Boston Red Sox",
      "abbreviation": "BOS",
      "division": "American League East",
      "league": "American League",
      "w": 32,
      "l": 46,
      "pct": ".410",
      "gb": "15.5",
      "previousGb": "14.5",
      "gbChange": -1,
      "wcGb": "6.0",
      "previousWcGb": "6.0",
      "wcGbChange": 0,
      "wcRank": "12",
      "clinchIndicator": null,
      "rs": 307,
      "ra": 314,
      "rd": -7,
      "pythWins": 38.1,
      "pythVar": -6.12,
      "streak": "L1",
      "splits": {
        "last10": "3-7",
        "home": "12-25",
        "away": "20-21",
        "division": null,
        "league": null,
        "winners": "14-21"
      },
      "stats": {
        "obp": 0.312,
        "slg": 0.385,
        "ops": 0.697,
        "fip": 3.93,
        "der": 0.694
      }
    },
    {
      "name": "Chicago Cubs",
      "abbreviation": "CHC",
      "division": "National League Central",
      "league": "National League",
      "w": 43,
      "l": 37,
      "pct": ".537",
      "gb": "7.0",
      "previousGb": "7.5",
      "gbChange": 0.5,
      "wcGb": "-",
      "previousWcGb": "-",
      "wcGbChange": null,
      "wcRank": "3",
      "clinchIndicator": null,
      "rs": 395,
      "ra": 359,
      "rd": 36,
      "pythWins": 43.8,
      "pythVar": -0.81,
      "streak": "W3",
      "splits": {
        "last10": "7-3",
        "home": "23-17",
        "away": "20-20",
        "division": null,
        "league": null,
        "winners": "22-22"
      },
      "stats": {
        "obp": 0.338,
        "slg": 0.406,
        "ops": 0.744,
        "fip": 4.69,
        "der": 0.726
      }
    },
    {
      "name": "Cincinnati Reds",
      "abbreviation": "CIN",
      "division": "National League Central",
      "league": "National League",
      "w": 37,
      "l": 42,
      "pct": ".468",
      "gb": "12.5",
      "previousGb": "11.5",
      "gbChange": -1,
      "wcGb": "5.5",
      "previousWcGb": "4.0",
      "wcGbChange": -1.5,
      "wcRank": "9",
      "clinchIndicator": null,
      "rs": 331,
      "ra": 381,
      "rd": -50,
      "pythWins": 34,
      "pythVar": 3.02,
      "streak": "L3",
      "splits": {
        "last10": "4-6",
        "home": "19-22",
        "away": "18-20",
        "division": null,
        "league": null,
        "winners": "15-31"
      },
      "stats": {
        "obp": 0.309,
        "slg": 0.389,
        "ops": 0.699,
        "fip": 4.93,
        "der": 0.703
      }
    },
    {
      "name": "Cleveland Guardians",
      "abbreviation": "CLE",
      "division": "American League Central",
      "league": "American League",
      "w": 42,
      "l": 39,
      "pct": ".519",
      "gb": "-",
      "previousGb": "1.0",
      "gbChange": null,
      "wcGb": "+2.5",
      "previousWcGb": "+1.5",
      "wcGbChange": -1,
      "wcRank": "2",
      "clinchIndicator": null,
      "rs": 320,
      "ra": 328,
      "rd": -8,
      "pythWins": 39.5,
      "pythVar": 2.5,
      "streak": "W1",
      "splits": {
        "last10": "4-6",
        "home": "19-17",
        "away": "23-22",
        "division": null,
        "league": null,
        "winners": "16-21"
      },
      "stats": {
        "obp": 0.313,
        "slg": 0.366,
        "ops": 0.679,
        "fip": 3.97,
        "der": 0.701
      }
    },
    {
      "name": "Colorado Rockies",
      "abbreviation": "COL",
      "division": "National League West",
      "league": "National League",
      "w": 32,
      "l": 49,
      "pct": ".395",
      "gb": "20.0",
      "previousGb": "20.0",
      "gbChange": 0,
      "wcGb": "11.5",
      "previousWcGb": "11.0",
      "wcGbChange": -0.5,
      "wcRank": "12",
      "clinchIndicator": null,
      "rs": 369,
      "ra": 459,
      "rd": -90,
      "pythWins": 31.8,
      "pythVar": 0.2,
      "streak": "W1",
      "splits": {
        "last10": "6-4",
        "home": "18-22",
        "away": "14-27",
        "division": null,
        "league": null,
        "winners": "13-35"
      },
      "stats": {
        "obp": 0.324,
        "slg": 0.41,
        "ops": 0.734,
        "fip": 4.77,
        "der": 0.667
      }
    },
    {
      "name": "Detroit Tigers",
      "abbreviation": "DET",
      "division": "American League Central",
      "league": "American League",
      "w": 34,
      "l": 46,
      "pct": ".425",
      "gb": "7.5",
      "previousGb": "7.5",
      "gbChange": 0,
      "wcGb": "5.0",
      "previousWcGb": "5.0",
      "wcGbChange": 0,
      "wcRank": "9",
      "clinchIndicator": null,
      "rs": 324,
      "ra": 330,
      "rd": -6,
      "pythWins": 39.3,
      "pythVar": -5.27,
      "streak": "L2",
      "splits": {
        "last10": "5-5",
        "home": "22-18",
        "away": "12-28",
        "division": null,
        "league": null,
        "winners": "19-20"
      },
      "stats": {
        "obp": 0.315,
        "slg": 0.392,
        "ops": 0.707,
        "fip": 3.92,
        "der": 0.703
      }
    },
    {
      "name": "Houston Astros",
      "abbreviation": "HOU",
      "division": "American League West",
      "league": "American League",
      "w": 39,
      "l": 43,
      "pct": ".476",
      "gb": "2.0",
      "previousGb": "3.5",
      "gbChange": 1.5,
      "wcGb": "1.0",
      "previousWcGb": "2.0",
      "wcGbChange": 1,
      "wcRank": "4",
      "clinchIndicator": null,
      "rs": 370,
      "ra": 409,
      "rd": -39,
      "pythWins": 36.9,
      "pythVar": 2.09,
      "streak": "W2",
      "splits": {
        "last10": "6-4",
        "home": "20-21",
        "away": "19-22",
        "division": null,
        "league": null,
        "winners": "12-20"
      },
      "stats": {
        "obp": 0.318,
        "slg": 0.412,
        "ops": 0.73,
        "fip": 4.73,
        "der": 0.705
      }
    },
    {
      "name": "Kansas City Royals",
      "abbreviation": "KC",
      "division": "American League Central",
      "league": "American League",
      "w": 34,
      "l": 48,
      "pct": ".415",
      "gb": "8.5",
      "previousGb": "8.0",
      "gbChange": -0.5,
      "wcGb": "6.0",
      "previousWcGb": "5.5",
      "wcGbChange": -0.5,
      "wcRank": "10",
      "clinchIndicator": null,
      "rs": 350,
      "ra": 399,
      "rd": -49,
      "pythWins": 35.7,
      "pythVar": -1.66,
      "streak": "L2",
      "splits": {
        "last10": "5-5",
        "home": "19-22",
        "away": "15-26",
        "division": null,
        "league": null,
        "winners": "18-27"
      },
      "stats": {
        "obp": 0.318,
        "slg": 0.394,
        "ops": 0.712,
        "fip": 4.57,
        "der": 0.697
      }
    },
    {
      "name": "Los Angeles Dodgers",
      "abbreviation": "LAD",
      "division": "National League West",
      "league": "National League",
      "w": 52,
      "l": 29,
      "pct": ".642",
      "gb": "-",
      "previousGb": "-",
      "gbChange": null,
      "wcGb": "-",
      "previousWcGb": "-",
      "wcGbChange": null,
      "wcRank": null,
      "clinchIndicator": null,
      "rs": 423,
      "ra": 279,
      "rd": 144,
      "pythWins": 56.4,
      "pythVar": -4.44,
      "streak": "W3",
      "splits": {
        "last10": "7-3",
        "home": "26-14",
        "away": "26-15",
        "division": null,
        "league": null,
        "winners": "26-17"
      },
      "stats": {
        "obp": 0.345,
        "slg": 0.438,
        "ops": 0.782,
        "fip": 3.7,
        "der": 0.734
      }
    },
    {
      "name": "Washington Nationals",
      "abbreviation": "WSH",
      "division": "National League East",
      "league": "National League",
      "w": 41,
      "l": 40,
      "pct": ".506",
      "gb": "8.0",
      "previousGb": "8.0",
      "gbChange": 0,
      "wcGb": "2.5",
      "previousWcGb": "1.0",
      "wcGbChange": -1.5,
      "wcRank": "8",
      "clinchIndicator": null,
      "rs": 433,
      "ra": 424,
      "rd": 9,
      "pythWins": 41.4,
      "pythVar": -0.35,
      "streak": "L2",
      "splits": {
        "last10": "5-5",
        "home": "17-24",
        "away": "24-16",
        "division": null,
        "league": null,
        "winners": "26-30"
      },
      "stats": {
        "obp": 0.321,
        "slg": 0.425,
        "ops": 0.746,
        "fip": 4.81,
        "der": 0.688
      }
    },
    {
      "name": "New York Mets",
      "abbreviation": "NYM",
      "division": "National League East",
      "league": "National League",
      "w": 34,
      "l": 46,
      "pct": ".425",
      "gb": "14.5",
      "previousGb": "14.0",
      "gbChange": -0.5,
      "wcGb": "9.0",
      "previousWcGb": "7.0",
      "wcGbChange": -2,
      "wcRank": "10",
      "clinchIndicator": null,
      "rs": 325,
      "ra": 371,
      "rd": -46,
      "pythWins": 34.7,
      "pythVar": -0.74,
      "streak": "L5",
      "splits": {
        "last10": "3-7",
        "home": "18-21",
        "away": "16-25",
        "division": null,
        "league": null,
        "winners": "20-32"
      },
      "stats": {
        "obp": 0.298,
        "slg": 0.376,
        "ops": 0.674,
        "fip": 3.94,
        "der": 0.694
      }
    },
    {
      "name": "Athletics",
      "abbreviation": "ATH",
      "division": "American League West",
      "league": "American League",
      "w": 38,
      "l": 42,
      "pct": ".475",
      "gb": "2.0",
      "previousGb": "2.5",
      "gbChange": 0.5,
      "wcGb": "1.0",
      "previousWcGb": "1.0",
      "wcGbChange": 0,
      "wcRank": "5",
      "clinchIndicator": null,
      "rs": 366,
      "ra": 423,
      "rd": -57,
      "pythWins": 34.3,
      "pythVar": 3.75,
      "streak": "L4",
      "splits": {
        "last10": "3-7",
        "home": "18-23",
        "away": "20-19",
        "division": null,
        "league": null,
        "winners": "16-23"
      },
      "stats": {
        "obp": 0.327,
        "slg": 0.415,
        "ops": 0.742,
        "fip": 4.79,
        "der": 0.689
      }
    },
    {
      "name": "Pittsburgh Pirates",
      "abbreviation": "PIT",
      "division": "National League Central",
      "league": "National League",
      "w": 41,
      "l": 40,
      "pct": ".506",
      "gb": "9.5",
      "previousGb": "10.0",
      "gbChange": 0.5,
      "wcGb": "2.5",
      "previousWcGb": "2.5",
      "wcGbChange": 0,
      "wcRank": "7",
      "clinchIndicator": null,
      "rs": 409,
      "ra": 382,
      "rd": 27,
      "pythWins": 43.3,
      "pythVar": -2.26,
      "streak": "W2",
      "splits": {
        "last10": "5-5",
        "home": "22-20",
        "away": "19-20",
        "division": null,
        "league": null,
        "winners": "19-26"
      },
      "stats": {
        "obp": 0.335,
        "slg": 0.411,
        "ops": 0.746,
        "fip": 3.87,
        "der": 0.689
      }
    },
    {
      "name": "San Diego Padres",
      "abbreviation": "SD",
      "division": "National League West",
      "league": "National League",
      "w": 42,
      "l": 37,
      "pct": ".532",
      "gb": "9.0",
      "previousGb": "9.0",
      "gbChange": 0,
      "wcGb": "0.5",
      "previousWcGb": "-",
      "wcGbChange": null,
      "wcRank": "4",
      "clinchIndicator": null,
      "rs": 309,
      "ra": 314,
      "rd": -5,
      "pythWins": 38.9,
      "pythVar": 3.13,
      "streak": "W3",
      "splits": {
        "last10": "6-4",
        "home": "22-19",
        "away": "20-18",
        "division": null,
        "league": null,
        "winners": "20-22"
      },
      "stats": {
        "obp": 0.294,
        "slg": 0.364,
        "ops": 0.659,
        "fip": 3.95,
        "der": 0.704
      }
    },
    {
      "name": "Seattle Mariners",
      "abbreviation": "SEA",
      "division": "American League West",
      "league": "American League",
      "w": 41,
      "l": 41,
      "pct": ".500",
      "gb": "-",
      "previousGb": "-",
      "gbChange": null,
      "wcGb": "-",
      "previousWcGb": "-",
      "wcGbChange": null,
      "wcRank": null,
      "clinchIndicator": null,
      "rs": 331,
      "ra": 327,
      "rd": 4,
      "pythWins": 41.5,
      "pythVar": -0.5,
      "streak": "L2",
      "splits": {
        "last10": "4-6",
        "home": "22-19",
        "away": "19-22",
        "division": null,
        "league": null,
        "winners": "16-18"
      },
      "stats": {
        "obp": 0.311,
        "slg": 0.384,
        "ops": 0.695,
        "fip": 3.55,
        "der": 0.691
      }
    },
    {
      "name": "San Francisco Giants",
      "abbreviation": "SF",
      "division": "National League West",
      "league": "National League",
      "w": 33,
      "l": 46,
      "pct": ".418",
      "gb": "18.0",
      "previousGb": "18.0",
      "gbChange": 0,
      "wcGb": "9.5",
      "previousWcGb": "9.0",
      "wcGbChange": -0.5,
      "wcRank": "11",
      "clinchIndicator": null,
      "rs": 322,
      "ra": 373,
      "rd": -51,
      "pythWins": 33.7,
      "pythVar": -0.73,
      "streak": "W2",
      "splits": {
        "last10": "5-5",
        "home": "16-20",
        "away": "17-26",
        "division": null,
        "league": null,
        "winners": "25-36"
      },
      "stats": {
        "obp": 0.309,
        "slg": 0.419,
        "ops": 0.728,
        "fip": 4.27,
        "der": 0.689
      }
    },
    {
      "name": "St. Louis Cardinals",
      "abbreviation": "STL",
      "division": "National League Central",
      "league": "National League",
      "w": 42,
      "l": 36,
      "pct": ".538",
      "gb": "7.0",
      "previousGb": "6.0",
      "gbChange": -1,
      "wcGb": "-",
      "previousWcGb": "+1.5",
      "wcGbChange": null,
      "wcRank": "2",
      "clinchIndicator": null,
      "rs": 359,
      "ra": 360,
      "rd": -1,
      "pythWins": 38.9,
      "pythVar": 3.11,
      "streak": "L2",
      "splits": {
        "last10": "4-6",
        "home": "22-19",
        "away": "20-17",
        "division": null,
        "league": null,
        "winners": "22-21"
      },
      "stats": {
        "obp": 0.327,
        "slg": 0.399,
        "ops": 0.726,
        "fip": 4.35,
        "der": 0.695
      }
    },
    {
      "name": "Tampa Bay Rays",
      "abbreviation": "TB",
      "division": "American League East",
      "league": "American League",
      "w": 45,
      "l": 33,
      "pct": ".577",
      "gb": "2.5",
      "previousGb": "3.0",
      "gbChange": 0.5,
      "wcGb": "+7.0",
      "previousWcGb": "+5.5",
      "wcGbChange": -1.5,
      "wcRank": "1",
      "clinchIndicator": null,
      "rs": 351,
      "ra": 338,
      "rd": 13,
      "pythWins": 40.5,
      "pythVar": 4.53,
      "streak": "W2",
      "splits": {
        "last10": "4-6",
        "home": "28-12",
        "away": "17-21",
        "division": null,
        "league": null,
        "winners": "18-17"
      },
      "stats": {
        "obp": 0.336,
        "slg": 0.388,
        "ops": 0.724,
        "fip": 4.16,
        "der": 0.712
      }
    },
    {
      "name": "Texas Rangers",
      "abbreviation": "TEX",
      "division": "American League West",
      "league": "American League",
      "w": 38,
      "l": 42,
      "pct": ".475",
      "gb": "2.0",
      "previousGb": "2.5",
      "gbChange": 0.5,
      "wcGb": "1.0",
      "previousWcGb": "1.0",
      "wcGbChange": 0,
      "wcRank": "6",
      "clinchIndicator": null,
      "rs": 319,
      "ra": 333,
      "rd": -14,
      "pythWins": 38.3,
      "pythVar": -0.28,
      "streak": "L2",
      "splits": {
        "last10": "4-6",
        "home": "19-18",
        "away": "19-24",
        "division": null,
        "league": null,
        "winners": "22-17"
      },
      "stats": {
        "obp": 0.317,
        "slg": 0.389,
        "ops": 0.706,
        "fip": 4.13,
        "der": 0.706
      }
    },
    {
      "name": "Toronto Blue Jays",
      "abbreviation": "TOR",
      "division": "American League East",
      "league": "American League",
      "w": 39,
      "l": 41,
      "pct": ".487",
      "gb": "9.5",
      "previousGb": "8.5",
      "gbChange": -1,
      "wcGb": "-",
      "previousWcGb": "-",
      "wcGbChange": null,
      "wcRank": "3",
      "clinchIndicator": null,
      "rs": 328,
      "ra": 355,
      "rd": -27,
      "pythWins": 36.8,
      "pythVar": 2.16,
      "streak": "L2",
      "splits": {
        "last10": "5-5",
        "home": "22-20",
        "away": "17-21",
        "division": null,
        "league": null,
        "winners": "16-26"
      },
      "stats": {
        "obp": 0.312,
        "slg": 0.392,
        "ops": 0.705,
        "fip": 4,
        "der": 0.691
      }
    },
    {
      "name": "Minnesota Twins",
      "abbreviation": "MIN",
      "division": "American League Central",
      "league": "American League",
      "w": 38,
      "l": 44,
      "pct": ".463",
      "gb": "4.5",
      "previousGb": "4.5",
      "gbChange": 0,
      "wcGb": "2.0",
      "previousWcGb": "2.0",
      "wcGbChange": 0,
      "wcRank": "8",
      "clinchIndicator": null,
      "rs": 395,
      "ra": 424,
      "rd": -29,
      "pythWins": 38.1,
      "pythVar": -0.1,
      "streak": "L3",
      "splits": {
        "last10": "6-4",
        "home": "20-22",
        "away": "18-22",
        "division": null,
        "league": null,
        "winners": "15-25"
      },
      "stats": {
        "obp": 0.322,
        "slg": 0.408,
        "ops": 0.73,
        "fip": 4.34,
        "der": 0.683
      }
    },
    {
      "name": "Philadelphia Phillies",
      "abbreviation": "PHI",
      "division": "National League East",
      "league": "National League",
      "w": 44,
      "l": 36,
      "pct": ".550",
      "gb": "4.5",
      "previousGb": "5.5",
      "gbChange": 1,
      "wcGb": "+1.0",
      "previousWcGb": "+1.5",
      "wcGbChange": 0.5,
      "wcRank": "1",
      "clinchIndicator": null,
      "rs": 349,
      "ra": 350,
      "rd": -1,
      "pythWins": 39.9,
      "pythVar": 4.11,
      "streak": "W2",
      "splits": {
        "last10": "6-4",
        "home": "23-19",
        "away": "21-17",
        "division": null,
        "league": null,
        "winners": "26-24"
      },
      "stats": {
        "obp": 0.3,
        "slg": 0.399,
        "ops": 0.7,
        "fip": 3.73,
        "der": 0.672
      }
    },
    {
      "name": "Atlanta Braves",
      "abbreviation": "ATL",
      "division": "National League East",
      "league": "National League",
      "w": 48,
      "l": 31,
      "pct": ".608",
      "gb": "-",
      "previousGb": "-",
      "gbChange": null,
      "wcGb": "-",
      "previousWcGb": "-",
      "wcGbChange": null,
      "wcRank": null,
      "clinchIndicator": null,
      "rs": 385,
      "ra": 293,
      "rd": 92,
      "pythWins": 50,
      "pythVar": -2.03,
      "streak": "L4",
      "splits": {
        "last10": "3-7",
        "home": "24-14",
        "away": "24-17",
        "division": null,
        "league": null,
        "winners": "28-19"
      },
      "stats": {
        "obp": 0.314,
        "slg": 0.416,
        "ops": 0.73,
        "fip": 3.96,
        "der": 0.718
      }
    },
    {
      "name": "Chicago White Sox",
      "abbreviation": "CWS",
      "division": "American League Central",
      "league": "American League",
      "w": 41,
      "l": 38,
      "pct": ".519",
      "gb": "-",
      "previousGb": "-",
      "gbChange": null,
      "wcGb": "-",
      "previousWcGb": "-",
      "wcGbChange": null,
      "wcRank": null,
      "clinchIndicator": null,
      "rs": 364,
      "ra": 367,
      "rd": -3,
      "pythWins": 39.2,
      "pythVar": 1.82,
      "streak": "L1",
      "splits": {
        "last10": "4-6",
        "home": "26-13",
        "away": "15-25",
        "division": null,
        "league": null,
        "winners": "19-22"
      },
      "stats": {
        "obp": 0.318,
        "slg": 0.41,
        "ops": 0.728,
        "fip": 4.39,
        "der": 0.703
      }
    },
    {
      "name": "Miami Marlins",
      "abbreviation": "MIA",
      "division": "National League East",
      "league": "National League",
      "w": 42,
      "l": 39,
      "pct": ".519",
      "gb": "7.0",
      "previousGb": "8.0",
      "gbChange": 1,
      "wcGb": "1.5",
      "previousWcGb": "1.0",
      "wcGbChange": -0.5,
      "wcRank": "5",
      "clinchIndicator": null,
      "rs": 349,
      "ra": 346,
      "rd": 3,
      "pythWins": 40.8,
      "pythVar": 1.15,
      "streak": "W2",
      "splits": {
        "last10": "7-3",
        "home": "28-17",
        "away": "14-22",
        "division": null,
        "league": null,
        "winners": "25-22"
      },
      "stats": {
        "obp": 0.323,
        "slg": 0.39,
        "ops": 0.713,
        "fip": 3.97,
        "der": 0.704
      }
    },
    {
      "name": "New York Yankees",
      "abbreviation": "NYY",
      "division": "American League East",
      "league": "American League",
      "w": 48,
      "l": 31,
      "pct": ".608",
      "gb": "-",
      "previousGb": "-",
      "gbChange": null,
      "wcGb": "-",
      "previousWcGb": "-",
      "wcGbChange": null,
      "wcRank": null,
      "clinchIndicator": null,
      "rs": 400,
      "ra": 287,
      "rd": 113,
      "pythWins": 52.2,
      "pythVar": -4.15,
      "streak": "W2",
      "splits": {
        "last10": "6-4",
        "home": "22-15",
        "away": "26-16",
        "division": null,
        "league": null,
        "winners": "11-12"
      },
      "stats": {
        "obp": 0.329,
        "slg": 0.437,
        "ops": 0.766,
        "fip": 3.59,
        "der": 0.709
      }
    },
    {
      "name": "Milwaukee Brewers",
      "abbreviation": "MIL",
      "division": "National League Central",
      "league": "National League",
      "w": 49,
      "l": 29,
      "pct": ".628",
      "gb": "-",
      "previousGb": "-",
      "gbChange": null,
      "wcGb": "-",
      "previousWcGb": "-",
      "wcGbChange": null,
      "wcRank": null,
      "clinchIndicator": null,
      "rs": 407,
      "ra": 284,
      "rd": 123,
      "pythWins": 52.5,
      "pythVar": -3.46,
      "streak": "W4",
      "splits": {
        "last10": "7-3",
        "home": "25-15",
        "away": "24-14",
        "division": null,
        "league": null,
        "winners": "30-17"
      },
      "stats": {
        "obp": 0.338,
        "slg": 0.391,
        "ops": 0.729,
        "fip": 3.49,
        "der": 0.707
      }
    }
  ]
}